lmoments3/__init__.py
lmoments3/distr.py
lmoments3/stats.py
lmoments3/tests/__init__.py
lmoments3/tests/test_lmoments.py
lmoments3/tests/test_samlmu_speed.py
lmoments3-1.0.8.dist-info/LICENSE
lmoments3-1.0.8.dist-info/METADATA
lmoments3-1.0.8.dist-info/WHEEL
lmoments3-1.0.8.dist-info/top_level.txt
lmoments3-1.0.8.dist-info/RECORD
