Metadata-Version: 2.1
Name: lmoments3
Version: 1.0.8
Summary: A library extend scipy with L-moments to calculate optimal parameters for a number of distributions
Author-email: "Florenz A.P. Hollebrandse" <f.a.p.hollebrandse@protonmail.ch>
Maintainer-email: Trevor James Smith <smith.trevorj@ouranos.ca>, Pascal Bourgault <bourgault.pascal@ouranos.ca>
License: GNU GENERAL PUBLIC LICENSE
Project-URL: Homepage, https://lmoments3.readthedocs.io/en
Project-URL: Source, https://github.com/Ouranosinc/lmoments3/
Project-URL: Changelog, https://github.com/Ouranosinc/lmoments3/blob/main/CHANGELOG.rst
Project-URL: Issue tracker, https://github.com/Ouranosinc/lmoments3/issues
Project-URL: About Ouranos, https://ouranos.ca/en/
Keywords: distributions,fitting,l-moments,linear-moments,lmoments,lmoments3,scipy,statistics
Classifier: Development Status :: 5 - Production/Stable
Classifier: Intended Audience :: Developers
Classifier: Intended Audience :: Science/Research
Classifier: License :: OSI Approved :: GNU General Public License v3 or later (GPLv3+)
Classifier: Natural Language :: English
Classifier: Operating System :: OS Independent
Classifier: Programming Language :: Python :: 3
Classifier: Programming Language :: Python :: 3.8
Classifier: Programming Language :: Python :: 3.9
Classifier: Programming Language :: Python :: 3.10
Classifier: Programming Language :: Python :: 3.11
Classifier: Programming Language :: Python :: 3.12
Classifier: Programming Language :: Python :: 3.13
Classifier: Topic :: Scientific/Engineering :: Mathematics
Requires-Python: >=3.8.0
License-File: LICENSE
Requires-Dist: numpy
Requires-Dist: scipy
Provides-Extra: dev
Requires-Dist: black >=24.8.0 ; extra == 'dev'
Requires-Dist: blackdoc >=0.3.9 ; extra == 'dev'
Requires-Dist: build >=1.0 ; extra == 'dev'
Requires-Dist: flake8 >=7.0.0 ; extra == 'dev'
Requires-Dist: pydocstyle >=6.3.0 ; extra == 'dev'
Requires-Dist: sphinx >=6.0.0 ; extra == 'dev'
Requires-Dist: sphinx-rtd-theme >=1.0 ; extra == 'dev'
Requires-Dist: wheel >=0.42.0 ; extra == 'dev'
